setup.cfg
setup.py
buildout/__init__.py
buildout.ucsdetector.egg-info/PKG-INFO
buildout.ucsdetector.egg-info/SOURCES.txt
buildout.ucsdetector.egg-info/dependency_links.txt
buildout.ucsdetector.egg-info/entry_points.txt
buildout.ucsdetector.egg-info/namespace_packages.txt
buildout.ucsdetector.egg-info/requires.txt
buildout.ucsdetector.egg-info/top_level.txt
buildout.ucsdetector.egg-info/zip-safe
buildout/ucsdetector/__init__.py
buildout/ucsdetector/tests.py