Metadata-Version: 1.0
Name: buildout.ucsdetector
Version: 0.5
Summary: A buildout extension that enables dependency links      to install eggs according to the UCS(Unicode Character Set)      version of the python distribution.
Home-page: http://github.com/dmpinheiro/buildout.ucsdetector
Author: Diego Manhaes Pinheiro
Author-email: dmpinheiro@gmail.com
License: MIT
Keywords: buildout ucs extension
Platform: UNKNOWN
Classifier: Framework :: Buildout
Classifier: Intended Audience :: Developers
Classifier: Topic :: Software Development :: Build Tools
Classifier: Topic :: Software Development :: Libraries :: Python Modules
